{
  "collectionName": "components_child_life_page_specialists",
  "info": {
    "displayName": "specialists",
    "description": ""
  },
  "options": {},
  "attributes": {
    "title": {
      "type": "string",
      "required": true
    },
    "description": {
      "type": "richtext",
      "required": true
    },
    "video": {
      "type": "media",
      "multiple": false,
      "required": true,
      "allowedTypes": [
        "images",
        "files",
        "videos",
        "audios"
      ]
    },
    "videoCover": {
      "allowedTypes": [
        "images",
        "files",
        "videos",
        "audios"
      ],
      "type": "media",
      "multiple": false,
      "required": true
    }
  }
}
